{"code":"PR-SW","name":"SWSH Black Star Promos","series":"Sword & Shield","cards":[{"name":"Grookey","imageUrl":"https://images.pokemontcg.io/swshp/SWSH001.png","imageUrlHiRes":"https://images.pokemontcg.io/swshp/SWSH001_hires.png","types":["Grass"],"supertype":"Pokémon","number":"SWSH001","rarity":"Promo"},{"name":"Scorbunny","imageUrl":"https://images.pokemontcg.io/swshp/SWSH002.png","imageUrlHiRes":"https://images.pokemontcg.io/swshp/SWSH002_hires.png","types":["Fire"],"supertype":"Pokémon","number":"SWSH002","rarity":"Promo"},{"name":"Sobble","imageUrl":"https://images.pokemontcg.io/swshp/SWSH003.png","imageUrlHiRes":"https://images.pokemontcg.io/swshp/SWSH003_hires.png","types":["Water"],"supertype":"Pokémon","number":"SWSH003","rarity":"Promo"},{"name":"Meowth V","imageUrl":"https://images.pokemontcg.io/swshp/SWSH004.png","imageUrlHiRes":"https://images.pokemontcg.io/swshp/SWSH004_hires.png","types":["Colorless"],"supertype":"Pokémon","number":"SWSH004","rarity":"Promo"},{"name":"Meowth VMAX","imageUrl":"https://images.pokemontcg.io/swshp/SWSH005.png","imageUrlHiRes":"https://images.pokemontcg.io/swshp/SWSH005_hires.png","types":["Colorless"],"supertype":"Pokémon","number":"SWSH005","rarity":"Promo"},{"name":"Rillaboom","imageUrl":"https://images.pokemontcg.io/swshp/SWSH006.png","imageUrlHiRes":"https://images.pokemontcg.io/swshp/SWSH006_hires.png","types":["Grass"],"supertype":"Pokémon","number":"SWSH006","rarity":"Promo"},{"name":"Frosmoth","imageUrl":"https://images.pokemontcg.io/swshp/SWSH007.png","imageUrlHiRes":"https://images.pokemontcg.io/swshp/SWSH007_hires.png","types":["Water"],"supertype":"Pokémon","number":"SWSH007","rarity":"Promo"},{"name":"Galarian Perrserker","imageUrl":"https://images.pokemontcg.io/swshp/SWSH008.png","imageUrlHiRes":"https://images.pokemontcg.io/swshp/SWSH008_hires.png","types":["Metal"],"supertype":"Pokémon","number":"SWSH008","rarity":"Promo"},{"name":"Cinccino","imageUrl":"https://images.pokemontcg.io/swshp/SWSH009.png","imageUrlHiRes":"https://images.pokemontcg.io/swshp/SWSH009_hires.png","types":["Colorless"],"supertype":"Pokémon","number":"SWSH009","rarity":"Promo"},{"name":"Gossifleur","imageUrl":"https://images.pokemontcg.io/swshp/SWSH010.png","imageUrlHiRes":"https://images.pokemontcg.io/swshp/SWSH010_hires.png","types":["Grass"],"supertype":"Pokémon","number":"SWSH010","rarity":"Promo"},{"name":"Wooloo","imageUrl":"https://images.pokemontcg.io/swshp/SWSH011.png","imageUrlHiRes":"https://images.pokemontcg.io/swshp/SWSH011_hires.png","types":["Colorless"],"supertype":"Pokémon","number":"SWSH011","rarity":"Promo"},{"name":"Morpeko","imageUrl":"https://images.pokemontcg.io/swshp/SWSH012.png","imageUrlHiRes":"https://images.pokemontcg.io/swshp/SWSH012_hires.png","types":["Lightning"],"supertype":"Pokémon","number":"SWSH012","rarity":"Promo"},{"name":"Galarian Ponyta","imageUrl":"https://images.pokemontcg.io/swshp/SWSH013.png","imageUrlHiRes":"https://images.pokemontcg.io/swshp/SWSH013_hires.png","types":["Psychic"],"supertype":"Pokémon","number":"SWSH013","rarity":"Promo"},{"name":"Rillaboom V","imageUrl":"https://images.pokemontcg.io/swshp/SWSH014.png","imageUrlHiRes":"https://images.pokemontcg.io/swshp/SWSH014_hires.png","types":["Grass"],"supertype":"Pokémon","number":"SWSH014","rarity":"Promo"},{"name":"Cinderace V","imageUrl":"https://images.pokemontcg.io/swshp/SWSH015.png","imageUrlHiRes":"https://images.pokemontcg.io/swshp/SWSH015_hires.png","types":["Fire"],"supertype":"Pokémon","number":"SWSH015","rarity":"Promo"},{"name":"Inteleon V","imageUrl":"https://images.pokemontcg.io/swshp/SWSH016.png","imageUrlHiRes":"https://images.pokemontcg.io/swshp/SWSH016_hires.png","types":["Water"],"supertype":"Pokémon","number":"SWSH016","rarity":"Promo"},{"name":"Toxtricity V","imageUrl":"https://images.pokemontcg.io/swshp/SWSH017.png","imageUrlHiRes":"https://images.pokemontcg.io/swshp/SWSH017_hires.png","types":["Lightning"],"supertype":"Pokémon","number":"SWSH017","rarity":"Promo"},{"name":"Zacian V","imageUrl":"https://images.pokemontcg.io/swshp/SWSH018.png","imageUrlHiRes":"https://images.pokemontcg.io/swshp/SWSH018_hires.png","types":["Metal"],"supertype":"Pokémon","number":"SWSH018","rarity":"Promo"},{"name":"Zamazenta V","imageUrl":"https://images.pokemontcg.io/swshp/SWSH019.png","imageUrlHiRes":"https://images.pokemontcg.io/swshp/SWSH019_hires.png","types":["Metal"],"supertype":"Pokémon","number":"SWSH019","rarity":"Promo"},{"name":"Pikachu","imageUrl":"https://images.pokemontcg.io/swshp/SWSH020.png","imageUrlHiRes":"https://images.pokemontcg.io/swshp/SWSH020_hires.png","types":["Lightning"],"supertype":"Pokémon","number":"SWSH020","rarity":"Promo"},{"name":"Polteageist V","imageUrl":"https://images.pokemontcg.io/swshp/SWSH021.png","imageUrlHiRes":"https://images.pokemontcg.io/swshp/SWSH021_hires.png","types":["Psychic"],"supertype":"Pokémon","number":"SWSH021","rarity":"Promo"},{"name":"Flapple","imageUrl":"https://images.pokemontcg.io/swshp/SWSH022.png","imageUrlHiRes":"https://images.pokemontcg.io/swshp/SWSH022_hires.png","types":["Grass"],"supertype":"Pokémon","number":"SWSH022","rarity":"Promo"},{"name":"Luxray","imageUrl":"https://images.pokemontcg.io/swshp/SWSH023.png","imageUrlHiRes":"https://images.pokemontcg.io/swshp/SWSH023_hires.png","types":["Lightning"],"supertype":"Pokémon","number":"SWSH023","rarity":"Promo"},{"name":"Coalossal","imageUrl":"https://images.pokemontcg.io/swshp/SWSH024.png","imageUrlHiRes":"https://images.pokemontcg.io/swshp/SWSH024_hires.png","types":["Fighting"],"supertype":"Pokémon","number":"SWSH024","rarity":"Promo"},{"name":"Garbodor","imageUrl":"https://images.pokemontcg.io/swshp/SWSH025.png","imageUrlHiRes":"https://images.pokemontcg.io/swshp/SWSH025_hires.png","types":["Darkness"],"supertype":"Pokémon","number":"SWSH025","rarity":"Promo"},{"name":"Mantine","imageUrl":"https://images.pokemontcg.io/swshp/SWSH026.png","imageUrlHiRes":"https://images.pokemontcg.io/swshp/SWSH026_hires.png","types":["Water"],"supertype":"Pokémon","number":"SWSH026","rarity":"Promo"},{"name":"Noctowl","imageUrl":"https://images.pokemontcg.io/swshp/SWSH027.png","imageUrlHiRes":"https://images.pokemontcg.io/swshp/SWSH027_hires.png","types":["Colorless"],"supertype":"Pokémon","number":"SWSH027","rarity":"Promo"},{"name":"Duraludon","imageUrl":"https://images.pokemontcg.io/swshp/SWSH028.png","imageUrlHiRes":"https://images.pokemontcg.io/swshp/SWSH028_hires.png","types":["Metal"],"supertype":"Pokémon","number":"SWSH028","rarity":"Promo"},{"name":"Rayquaza","imageUrl":"https://images.pokemontcg.io/swshp/SWSH029.png","imageUrlHiRes":"https://images.pokemontcg.io/swshp/SWSH029_hires.png","types":["Colorless"],"supertype":"Pokémon","number":"SWSH029","rarity":"Promo"},{"name":"Copperajah V","imageUrl":"https://images.pokemontcg.io/swshp/SWSH030.png","imageUrlHiRes":"https://images.pokemontcg.io/swshp/SWSH030_hires.png","types":["Metal"],"supertype":"Pokémon","number":"SWSH030","rarity":"Promo"},{"name":"Morpeko","imageUrl":"https://images.pokemontcg.io/swshp/SWSH031.png","imageUrlHiRes":"https://images.pokemontcg.io/swshp/SWSH031_hires.png","types":["Lightning"],"supertype":"Pokémon","number":"SWSH031","rarity":"Promo"},{"name":"Snorlax","imageUrl":"https://images.pokemontcg.io/swshp/SWSH032.png","imageUrlHiRes":"https://images.pokemontcg.io/swshp/SWSH032_hires.png","types":["Colorless"],"supertype":"Pokémon","number":"SWSH032","rarity":"Promo"},{"name":"Zacian","imageUrl":"https://images.pokemontcg.io/swshp/SWSH033.png","imageUrlHiRes":"https://images.pokemontcg.io/swshp/SWSH033_hires.png","types":["Metal"],"supertype":"Pokémon","number":"SWSH033","rarity":"Promo"},{"name":"Zamazenta","imageUrl":"https://images.pokemontcg.io/swshp/SWSH034.png","imageUrlHiRes":"https://images.pokemontcg.io/swshp/SWSH034_hires.png","types":["Metal"],"supertype":"Pokémon","number":"SWSH034","rarity":"Promo"},{"name":"Decidueye","imageUrl":"https://images.pokemontcg.io/swshp/SWSH035.png","imageUrlHiRes":"https://images.pokemontcg.io/swshp/SWSH035_hires.png","types":["Grass"],"supertype":"Pokémon","number":"SWSH035","rarity":"Promo"},{"name":"Arctozolt","imageUrl":"https://images.pokemontcg.io/swshp/SWSH036.png","imageUrlHiRes":"https://images.pokemontcg.io/swshp/SWSH036_hires.png","types":["Lightning"],"supertype":"Pokémon","number":"SWSH036","rarity":"Promo"},{"name":"Hydreigon","imageUrl":"https://images.pokemontcg.io/swshp/SWSH037.png","imageUrlHiRes":"https://images.pokemontcg.io/swshp/SWSH037_hires.png","types":["Darkness"],"supertype":"Pokémon","number":"SWSH037","rarity":"Promo"},{"name":"Kangaskhan","imageUrl":"https://images.pokemontcg.io/swshp/SWSH038.png","imageUrlHiRes":"https://images.pokemontcg.io/swshp/SWSH038_hires.png","types":["Colorless"],"supertype":"Pokémon","number":"SWSH038","rarity":"Promo"},{"name":"Pikachu","imageUrl":"https://images.pokemontcg.io/swshp/SWSH039.png","imageUrlHiRes":"https://images.pokemontcg.io/swshp/SWSH039_hires.png","types":["Lightning"],"supertype":"Pokémon","number":"SWSH039","rarity":"Promo"},{"name":"Hatenna","imageUrl":"https://images.pokemontcg.io/swshp/SWSH040.png","imageUrlHiRes":"https://images.pokemontcg.io/swshp/SWSH040_hires.png","types":["Psychic"],"supertype":"Pokémon","number":"SWSH040","rarity":"Promo"},{"name":"Flareon","imageUrl":"https://images.pokemontcg.io/swshp/SWSH041.png","imageUrlHiRes":"https://images.pokemontcg.io/swshp/SWSH041_hires.png","types":["Fire"],"supertype":"Pokémon","number":"SWSH041","rarity":"Promo"},{"name":"Eevee","imageUrl":"https://images.pokemontcg.io/swshp/SWSH042.png","imageUrlHiRes":"https://images.pokemontcg.io/swshp/SWSH042_hires.png","types":["Colorless"],"supertype":"Pokémon","number":"SWSH042","rarity":"Promo"},{"name":"Galarian Sirfetch'd V","imageUrl":"https://images.pokemontcg.io/swshp/SWSH043.png","imageUrlHiRes":"https://images.pokemontcg.io/swshp/SWSH043_hires.png","types":["Fighting"],"supertype":"Pokémon","number":"SWSH043","rarity":"Promo"},{"name":"Eternatus V","imageUrl":"https://images.pokemontcg.io/swshp/SWSH044.png","imageUrlHiRes":"https://images.pokemontcg.io/swshp/SWSH044_hires.png","types":["Darkness"],"supertype":"Pokémon","number":"SWSH044","rarity":"Promo"},{"name":"Eternatus VMAX","imageUrl":"https://images.pokemontcg.io/swshp/SWSH045.png","imageUrlHiRes":"https://images.pokemontcg.io/swshp/SWSH045_hires.png","types":["Darkness"],"supertype":"Pokémon","number":"SWSH045","rarity":"Promo"},{"name":"Eldegoss","imageUrl":"https://images.pokemontcg.io/swshp/SWSH046.png","imageUrlHiRes":"https://images.pokemontcg.io/swshp/SWSH046_hires.png","types":["Grass"],"supertype":"Pokémon","number":"SWSH046","rarity":"Promo"},{"name":"Drednaw","imageUrl":"https://images.pokemontcg.io/swshp/SWSH047.png","imageUrlHiRes":"https://images.pokemontcg.io/swshp/SWSH047_hires.png","types":["Water"],"supertype":"Pokémon","number":"SWSH047","rarity":"Promo"},{"name":"Centiskorch","imageUrl":"https://images.pokemontcg.io/swshp/SWSH048.png","imageUrlHiRes":"https://images.pokemontcg.io/swshp/SWSH048_hires.png","types":["Fire"],"supertype":"Pokémon","number":"SWSH048","rarity":"Promo"},{"name":"Dubwool V","imageUrl":"https://images.pokemontcg.io/swshp/SWSH049.png","imageUrlHiRes":"https://images.pokemontcg.io/swshp/SWSH049_hires.png","types":["Colorless"],"supertype":"Pokémon","number":"SWSH049","rarity":"Promo"},{"name":"Charizard V","imageUrl":"https://images.pokemontcg.io/swshp/SWSH050.png","imageUrlHiRes":"https://images.pokemontcg.io/swshp/SWSH050_hires.png","types":["Fire"],"supertype":"Pokémon","number":"SWSH050","rarity":"Promo"},{"name":"Lapras","imageUrl":"https://images.pokemontcg.io/swshp/SWSH051.png","imageUrlHiRes":"https://images.pokemontcg.io/swshp/SWSH051_hires.png","types":["Water"],"supertype":"Pokémon","number":"SWSH051","rarity":"Promo"},{"name":"Gengar","imageUrl":"https://images.pokemontcg.io/swshp/SWSH052.png","imageUrlHiRes":"https://images.pokemontcg.io/swshp/SWSH052_hires.png","types":["Psychic"],"supertype":"Pokémon","number":"SWSH052","rarity":"Promo"},{"name":"Machamp","imageUrl":"https://images.pokemontcg.io/swshp/SWSH053.png","imageUrlHiRes":"https://images.pokemontcg.io/swshp/SWSH053_hires.png","types":["Fighting"],"supertype":"Pokémon","number":"SWSH053","rarity":"Promo"},{"name":"Coalossal","imageUrl":"https://images.pokemontcg.io/swshp/SWSH054.png","imageUrlHiRes":"https://images.pokemontcg.io/swshp/SWSH054_hires.png","types":["Fighting"],"supertype":"Pokémon","number":"SWSH054","rarity":"Promo"},{"name":"Hatterene V","imageUrl":"https://images.pokemontcg.io/swshp/SWSH055.png","imageUrlHiRes":"https://images.pokemontcg.io/swshp/SWSH055_hires.png","types":["Psychic"],"supertype":"Pokémon","number":"SWSH055","rarity":"Promo"},{"name":"Morpeko V","imageUrl":"https://images.pokemontcg.io/swshp/SWSH056.png","imageUrlHiRes":"https://images.pokemontcg.io/swshp/SWSH056_hires.png","types":["Lightning"],"supertype":"Pokémon","number":"SWSH056","rarity":"Promo"},{"name":"Grimmsnarl V","imageUrl":"https://images.pokemontcg.io/swshp/SWSH057.png","imageUrlHiRes":"https://images.pokemontcg.io/swshp/SWSH057_hires.png","types":["Darkness"],"supertype":"Pokémon","number":"SWSH057","rarity":"Promo"},{"name":"Alcremie","imageUrl":"https://images.pokemontcg.io/swshp/SWSH058.png","imageUrlHiRes":"https://images.pokemontcg.io/swshp/SWSH058_hires.png","types":["Psychic"],"supertype":"Pokémon","number":"SWSH058","rarity":"Promo"},{"name":"Galarian Obstagoon","imageUrl":"https://images.pokemontcg.io/swshp/SWSH059.png","imageUrlHiRes":"https://images.pokemontcg.io/swshp/SWSH059_hires.png","types":["Darkness"],"supertype":"Pokémon","number":"SWSH059","rarity":"Promo"},{"name":"Duraludon","imageUrl":"https://images.pokemontcg.io/swshp/SWSH060.png","imageUrlHiRes":"https://images.pokemontcg.io/swshp/SWSH060_hires.png","types":["Metal"],"supertype":"Pokémon","number":"SWSH060","rarity":"Promo"},{"name":"Pikachu V","imageUrl":"https://images.pokemontcg.io/swshp/SWSH063.png","imageUrlHiRes":"https://images.pokemontcg.io/swshp/SWSH063_hires.png","types":["Lightning"],"supertype":"Pokémon","number":"SWSH063","rarity":"Promo"},{"name":"Eternatus V","imageUrl":"https://images.pokemontcg.io/swshp/SWSH064.png","imageUrlHiRes":"https://images.pokemontcg.io/swshp/SWSH064_hires.png","types":["Darkness"],"supertype":"Pokémon","number":"SWSH064","rarity":"Promo"},{"name":"Eevee V","imageUrl":"https://images.pokemontcg.io/swshp/SWSH065.png","imageUrlHiRes":"https://images.pokemontcg.io/swshp/SWSH065_hires.png","types":["Colorless"],"supertype":"Pokémon","number":"SWSH065","rarity":"Promo"},{"name":"Charizard","imageUrl":"https://images.pokemontcg.io/swshp/SWSH066.png","imageUrlHiRes":"https://images.pokemontcg.io/swshp/SWSH066_hires.png","types":["Fire"],"supertype":"Pokémon","number":"SWSH066","rarity":"Promo"},{"name":"Donphan","imageUrl":"https://images.pokemontcg.io/swshp/SWSH067.png","imageUrlHiRes":"https://images.pokemontcg.io/swshp/SWSH067_hires.png","types":["Fighting"],"supertype":"Pokémon","number":"SWSH067","rarity":"Promo"},{"name":"Snorlax","imageUrl":"https://images.pokemontcg.io/swshp/SWSH068.png","imageUrlHiRes":"https://images.pokemontcg.io/swshp/SWSH068_hires.png","types":["Colorless"],"supertype":"Pokémon","number":"SWSH068","rarity":"Promo"},{"name":"Lugia","imageUrl":"https://images.pokemontcg.io/swshp/SWSH069.png","imageUrlHiRes":"https://images.pokemontcg.io/swshp/SWSH069_hires.png","types":["Colorless"],"supertype":"Pokémon","number":"SWSH069","rarity":"Promo"},{"name":"Grookey","imageUrl":"https://images.pokemontcg.io/swshp/SWSH070.png","imageUrlHiRes":"https://images.pokemontcg.io/swshp/SWSH070_hires.png","types":["Grass"],"supertype":"Pokémon","number":"SWSH070","rarity":"Promo"},{"name":"Scorbunny","imageUrl":"https://images.pokemontcg.io/swshp/SWSH071.png","imageUrlHiRes":"https://images.pokemontcg.io/swshp/SWSH071_hires.png","types":["Fire"],"supertype":"Pokémon","number":"SWSH071","rarity":"Promo"},{"name":"Vaporeon","imageUrl":"https://images.pokemontcg.io/swshp/SWSH072.png","imageUrlHiRes":"https://images.pokemontcg.io/swshp/SWSH072_hires.png","types":["Water"],"supertype":"Pokémon","number":"SWSH072","rarity":"Promo"},{"name":"Sobble","imageUrl":"https://images.pokemontcg.io/swshp/SWSH073.png","imageUrlHiRes":"https://images.pokemontcg.io/swshp/SWSH073_hires.png","types":["Water"],"supertype":"Pokémon","number":"SWSH073","rarity":"Promo"},{"name":"Special Delivery Pikachu","imageUrl":"https://images.pokemontcg.io/swshp/SWSH074.png","imageUrlHiRes":"https://images.pokemontcg.io/swshp/SWSH074_hires.png","types":["Lightning"],"supertype":"Pokémon","number":"SWSH074","rarity":"Promo"},{"name":"Pikachu V","imageUrl":"https://images.pokemontcg.io/swshp/SWSH061.png","imageUrlHiRes":"https://images.pokemontcg.io/swshp/SWSH061_hires.png","types":["Lightning"],"supertype":"Pokémon","number":"SWSH061","rarity":"Promo"},{"name":"Zacian V","imageUrl":"https://images.pokemontcg.io/swshp/SWSH076.png","imageUrlHiRes":"https://images.pokemontcg.io/swshp/SWSH076_hires.png","types":["Metal"],"supertype":"Pokémon","number":"SWSH076","rarity":"Promo"},{"name":"Zamazenta V","imageUrl":"https://images.pokemontcg.io/swshp/SWSH077.png","imageUrlHiRes":"https://images.pokemontcg.io/swshp/SWSH077_hires.png","types":["Metal"],"supertype":"Pokémon","number":"SWSH077","rarity":"Promo"},{"name":"Orbeetle V","imageUrl":"https://images.pokemontcg.io/swshp/SWSH078.png","imageUrlHiRes":"https://images.pokemontcg.io/swshp/SWSH078_hires.png","types":["Grass"],"supertype":"Pokémon","number":"SWSH078","rarity":"Promo"},{"name":"Galarian Mr. Rime","imageUrl":"https://images.pokemontcg.io/swshp/SWSH079.png","imageUrlHiRes":"https://images.pokemontcg.io/swshp/SWSH079_hires.png","types":["Water"],"supertype":"Pokémon","number":"SWSH079","rarity":"Promo"},{"name":"Dedenne","imageUrl":"https://images.pokemontcg.io/swshp/SWSH080.png","imageUrlHiRes":"https://images.pokemontcg.io/swshp/SWSH080_hires.png","types":["Psychic"],"supertype":"Pokémon","number":"SWSH080","rarity":"Promo"},{"name":"Polteageist","imageUrl":"https://images.pokemontcg.io/swshp/SWSH081.png","imageUrlHiRes":"https://images.pokemontcg.io/swshp/SWSH081_hires.png","types":["Psychic"],"supertype":"Pokémon","number":"SWSH081","rarity":"Promo"},{"name":"Bunnelby","imageUrl":"https://images.pokemontcg.io/swshp/SWSH082.png","imageUrlHiRes":"https://images.pokemontcg.io/swshp/SWSH082_hires.png","types":["Colorless"],"supertype":"Pokémon","number":"SWSH082","rarity":"Promo"},{"name":"Alakazam V","imageUrl":"https://images.pokemontcg.io/swshp/SWSH083.png","imageUrlHiRes":"https://images.pokemontcg.io/swshp/SWSH083_hires.png","types":["Psychic"],"supertype":"Pokémon","number":"SWSH083","rarity":"Promo"},{"name":"Eldegoss V","imageUrl":"https://images.pokemontcg.io/swshp/SWSH084.png","imageUrlHiRes":"https://images.pokemontcg.io/swshp/SWSH084_hires.png","types":["Grass"],"supertype":"Pokémon","number":"SWSH084","rarity":"Promo"},{"name":"Boltund V","imageUrl":"https://images.pokemontcg.io/swshp/SWSH085.png","imageUrlHiRes":"https://images.pokemontcg.io/swshp/SWSH085_hires.png","types":["Lightning"],"supertype":"Pokémon","number":"SWSH085","rarity":"Promo"},{"name":"Cramorant V","imageUrl":"https://images.pokemontcg.io/swshp/SWSH086.png","imageUrlHiRes":"https://images.pokemontcg.io/swshp/SWSH086_hires.png","types":["Colorless"],"supertype":"Pokémon","number":"SWSH086","rarity":"Promo"},{"name":"Eevee VMAX","imageUrl":"https://images.pokemontcg.io/swshp/SWSH087.png","imageUrlHiRes":"https://images.pokemontcg.io/swshp/SWSH087_hires.png","types":["Colorless"],"supertype":"Pokémon","number":"SWSH087","rarity":"Promo"},{"name":"Dragapult V","imageUrl":"https://images.pokemontcg.io/swshp/SWSH096.png","imageUrlHiRes":"https://images.pokemontcg.io/swshp/SWSH096_hires.png","types":["Psychic"],"supertype":"Pokémon","number":"SWSH096","rarity":"Promo"},{"name":"Dragapult VMAX","imageUrl":"https://images.pokemontcg.io/swshp/SWSH097.png","imageUrlHiRes":"https://images.pokemontcg.io/swshp/SWSH097_hires.png","types":["Psychic"],"supertype":"Pokémon","number":"SWSH097","rarity":"Promo"},{"name":"Crobat V","imageUrl":"https://images.pokemontcg.io/swshp/SWSH098.png","imageUrlHiRes":"https://images.pokemontcg.io/swshp/SWSH098_hires.png","types":["Darkness"],"supertype":"Pokémon","number":"SWSH098","rarity":"Promo"},{"name":"Crobat VMAX","imageUrl":"https://images.pokemontcg.io/swshp/SWSH099.png","imageUrlHiRes":"https://images.pokemontcg.io/swshp/SWSH099_hires.png","types":["Darkness"],"supertype":"Pokémon","number":"SWSH099","rarity":"Promo"},{"name":"Venusaur V","imageUrl":"https://images.pokemontcg.io/swshp/SWSH100.png","imageUrlHiRes":"https://images.pokemontcg.io/swshp/SWSH100_hires.png","types":["Grass"],"supertype":"Pokémon","number":"SWSH100","rarity":"Promo"},{"name":"Blastoise V","imageUrl":"https://images.pokemontcg.io/swshp/SWSH101.png","imageUrlHiRes":"https://images.pokemontcg.io/swshp/SWSH101_hires.png","types":["Water"],"supertype":"Pokémon","number":"SWSH101","rarity":"Promo"},{"name":"Cherrim","imageUrl":"https://images.pokemontcg.io/swshp/SWSH088.png","imageUrlHiRes":"https://images.pokemontcg.io/swshp/SWSH088_hires.png","types":["Grass"],"supertype":"Pokémon","number":"SWSH088","rarity":"Promo"},{"name":"Octillery","imageUrl":"https://images.pokemontcg.io/swshp/SWSH089.png","imageUrlHiRes":"https://images.pokemontcg.io/swshp/SWSH089_hires.png","types":["Water"],"supertype":"Pokémon","number":"SWSH089","rarity":"Promo"},{"name":"Houndoom","imageUrl":"https://images.pokemontcg.io/swshp/SWSH090.png","imageUrlHiRes":"https://images.pokemontcg.io/swshp/SWSH090_hires.png","types":["Darkness"],"supertype":"Pokémon","number":"SWSH090","rarity":"Promo"},{"name":"Bronzong","imageUrl":"https://images.pokemontcg.io/swshp/SWSH091.png","imageUrlHiRes":"https://images.pokemontcg.io/swshp/SWSH091_hires.png","types":["Metal"],"supertype":"Pokémon","number":"SWSH091","rarity":"Promo"},{"name":"Charmander","imageUrl":"https://images.pokemontcg.io/swshp/SWSH092.png","imageUrlHiRes":"https://images.pokemontcg.io/swshp/SWSH092_hires.png","types":["Fire"],"supertype":"Pokémon","number":"SWSH092","rarity":"Promo"},{"name":"Arrokuda","imageUrl":"https://images.pokemontcg.io/swshp/SWSH093.png","imageUrlHiRes":"https://images.pokemontcg.io/swshp/SWSH093_hires.png","types":["Water"],"supertype":"Pokémon","number":"SWSH093","rarity":"Promo"},{"name":"Jolteon","imageUrl":"https://images.pokemontcg.io/swshp/SWSH094.png","imageUrlHiRes":"https://images.pokemontcg.io/swshp/SWSH094_hires.png","types":["Lightning"],"supertype":"Pokémon","number":"SWSH094","rarity":"Promo"},{"name":"Eevee","imageUrl":"https://images.pokemontcg.io/swshp/SWSH095.png","imageUrlHiRes":"https://images.pokemontcg.io/swshp/SWSH095_hires.png","types":["Colorless"],"supertype":"Pokémon","number":"SWSH095","rarity":"Promo"},{"name":"Venusaur VMAX","imageUrl":"https://images.pokemontcg.io/swshp/SWSH102.png","imageUrlHiRes":"https://images.pokemontcg.io/swshp/SWSH102_hires.png","types":["Grass"],"supertype":"Pokémon","number":"SWSH102","rarity":"Promo"},{"name":"Blastoise VMAX","imageUrl":"https://images.pokemontcg.io/swshp/SWSH103.png","imageUrlHiRes":"https://images.pokemontcg.io/swshp/SWSH103_hires.png","types":["Water"],"supertype":"Pokémon","number":"SWSH103","rarity":"Promo"},{"name":"Single Strike Urshifu V","imageUrl":"https://images.pokemontcg.io/swshp/SWSH106.png","imageUrlHiRes":"https://images.pokemontcg.io/swshp/SWSH106_hires.png","types":["Fighting"],"supertype":"Pokémon","number":"SWSH106","rarity":"Promo"},{"name":"Rapid Strike Urshifu V","imageUrl":"https://images.pokemontcg.io/swshp/SWSH107.png","imageUrlHiRes":"https://images.pokemontcg.io/swshp/SWSH107_hires.png","types":["Fighting"],"supertype":"Pokémon","number":"SWSH107","rarity":"Promo"},{"name":"Victini V","imageUrl":"https://images.pokemontcg.io/swshp/SWSH104.png","imageUrlHiRes":"https://images.pokemontcg.io/swshp/SWSH104_hires.png","types":["Fire"],"supertype":"Pokémon","number":"SWSH104","rarity":"Promo"},{"name":"Gardevoir V","imageUrl":"https://images.pokemontcg.io/swshp/SWSH105.png","imageUrlHiRes":"https://images.pokemontcg.io/swshp/SWSH105_hires.png","types":["Psychic"],"supertype":"Pokémon","number":"SWSH105","rarity":"Promo"},{"name":"Empoleon V","imageUrl":"https://images.pokemontcg.io/swshp/SWSH108.png","imageUrlHiRes":"https://images.pokemontcg.io/swshp/SWSH108_hires.png","types":["Water"],"supertype":"Pokémon","number":"SWSH108","rarity":"Promo"},{"name":"Tyranitar V","imageUrl":"https://images.pokemontcg.io/swshp/SWSH109.png","imageUrlHiRes":"https://images.pokemontcg.io/swshp/SWSH109_hires.png","types":["Darkness"],"supertype":"Pokémon","number":"SWSH109","rarity":"Promo"},{"name":"Galarian Rapidash V","imageUrl":"https://images.pokemontcg.io/swshp/SWSH111.png","imageUrlHiRes":"https://images.pokemontcg.io/swshp/SWSH111_hires.png","types":["Psychic"],"supertype":"Pokémon","number":"SWSH111","rarity":"Promo"},{"name":"Cinderace","imageUrl":"https://images.pokemontcg.io/swshp/SWSH112.png","imageUrlHiRes":"https://images.pokemontcg.io/swshp/SWSH112_hires.png","types":["Fire"],"supertype":"Pokémon","number":"SWSH112","rarity":"Promo"},{"name":"Inteleon","imageUrl":"https://images.pokemontcg.io/swshp/SWSH113.png","imageUrlHiRes":"https://images.pokemontcg.io/swshp/SWSH113_hires.png","types":["Water"],"supertype":"Pokémon","number":"SWSH113","rarity":"Promo"},{"name":"Cresselia","imageUrl":"https://images.pokemontcg.io/swshp/SWSH114.png","imageUrlHiRes":"https://images.pokemontcg.io/swshp/SWSH114_hires.png","types":["Psychic"],"supertype":"Pokémon","number":"SWSH114","rarity":"Promo"},{"name":"Passimian","imageUrl":"https://images.pokemontcg.io/swshp/SWSH115.png","imageUrlHiRes":"https://images.pokemontcg.io/swshp/SWSH115_hires.png","types":["Fighting"],"supertype":"Pokémon","number":"SWSH115","rarity":"Promo"},{"name":"Morpeko","imageUrl":"https://images.pokemontcg.io/swshp/SWSH116.png","imageUrlHiRes":"https://images.pokemontcg.io/swshp/SWSH116_hires.png","types":["Lightning"],"supertype":"Pokémon","number":"SWSH116","rarity":"Promo"},{"name":"Phanpy","imageUrl":"https://images.pokemontcg.io/swshp/SWSH117.png","imageUrlHiRes":"https://images.pokemontcg.io/swshp/SWSH117_hires.png","types":["Fighting"],"supertype":"Pokémon","number":"SWSH117","rarity":"Promo"},{"name":"Eevee","imageUrl":"https://images.pokemontcg.io/swshp/SWSH118.png","imageUrlHiRes":"https://images.pokemontcg.io/swshp/SWSH118_hires.png","types":["Colorless"],"supertype":"Pokémon","number":"SWSH118","rarity":"Promo"},{"name":"Snorlax","imageUrl":"https://images.pokemontcg.io/swshp/SWSH119.png","imageUrlHiRes":"https://images.pokemontcg.io/swshp/SWSH119_hires.png","types":["Colorless"],"supertype":"Pokémon","number":"SWSH119","rarity":"Promo"},{"name":"Professor's Research","imageUrl":"https://images.pokemontcg.io/swshp/SWSH178.png","imageUrlHiRes":"https://images.pokemontcg.io/swshp/SWSH178_hires.png","supertype":"Trainer","number":"SWSH178","rarity":"Promo"}]}